admin_auth0/__init__.py
admin_auth0/auth0.py
admin_auth0/authentication.py
admin_auth0/urls.py
admin_auth0/views.py
admin_auth0-0.2.10.dist-info/METADATA
admin_auth0-0.2.10.dist-info/WHEEL
admin_auth0-0.2.10.dist-info/RECORD
