Metadata-Version: 2.1
Name: admin_auth0
Version: 0.2.10
Summary: 
Author: Serhii Lakodei
Author-email: serhii.lakodei@gmail.com
Requires-Python: >=3.9,<4.0
Classifier: Programming Language :: Python :: 3
Classifier: Programming Language :: Python :: 3.9
Classifier: Programming Language :: Python :: 3.10
Classifier: Programming Language :: Python :: 3.11
Classifier: Programming Language :: Python :: 3.12
Requires-Dist: authlib (>=1.3.0)
Requires-Dist: build (>=1.0.3)
Requires-Dist: django (>=4.2.2)
Requires-Dist: django-environ (>=0.10.0)
Requires-Dist: pyjwt (>=2.8.0)
Requires-Dist: twine (>=4.0.2)
